credgem/__init__.py
credgem/api/base.py
credgem/api/credit_types.py
credgem/api/insights.py
credgem/api/transactions.py
credgem/api/wallets.py
credgem/contexts.py
credgem/exceptions.py
credgem/models/__init__.py
credgem/models/credit_types.py
credgem/models/insights.py
credgem/models/transactions.py
credgem/models/wallets.py
credgem/utils.py
credgem_sdk-0.1.7.dist-info/METADATA
credgem_sdk-0.1.7.dist-info/WHEEL
credgem_sdk-0.1.7.dist-info/RECORD
