Metadata-Version: 2.1
Name: credgem-sdk
Version: 0.1.7
Summary: Python SDK for CredGem API - A powerful credit management system
Home-page: https://credgem.com
License: MIT
Keywords: credits,wallet,payments,virtual-currency
Author: CredGem
Author-email: support@credgem.com
Requires-Python: >=3.9,<4.0
Classifier: Development Status :: 4 - Beta
Classifier: Intended Audience :: Developers
Classifier: License :: OSI Approved :: MIT License
Classifier: Operating System :: OS Independent
Classifier: Programming Language :: Python :: 3
Classifier: Programming Language :: Python :: 3.9
Classifier: Programming Language :: Python :: 3.10
Classifier: Programming Language :: Python :: 3.11
Classifier: Programming Language :: Python :: 3.12
Classifier: Programming Language :: Python :: 3.8
Classifier: Topic :: Software Development :: Libraries :: Python Modules
Requires-Dist: httpx (>=0.25.0,<0.26.0)
Project-URL: Documentation, https://docs.credgem.com
Project-URL: Repository, https://github.com/CredGem/CredGem
